ignoreexceptions/README.MD
ignoreexceptions/__init__.py
ignoreexceptions/requirements.txt
ignoreexceptions/thirdparty.json
ignoreexceptions-0.11.dist-info/LICENSE.rst
ignoreexceptions-0.11.dist-info/METADATA
ignoreexceptions-0.11.dist-info/WHEEL
ignoreexceptions-0.11.dist-info/top_level.txt
ignoreexceptions-0.11.dist-info/RECORD
