Metadata-Version: 2.1
Name: ignoreexceptions
Version: 0.11
Summary: Decorators that provide graceful exception handling, customization of error handling behavior, error logging
Home-page: https://github.com/hansalemaos/ignoreexceptions
Author: Johannes Fischer
Author-email: aulasparticularesdealemaosp@gmail.com
License: MIT
Keywords: ignore,exceptions,decorator
Classifier: Development Status :: 4 - Beta
Classifier: Programming Language :: Python :: 3 :: Only
Classifier: Programming Language :: Python :: 3.10
Classifier: Topic :: Software Development :: Libraries :: Python Modules
Classifier: Topic :: Utilities
License-File: LICENSE.rst
Requires-Dist: touchtouch
